github_standup_agent/__init__.py
github_standup_agent/__main__.py
github_standup_agent/cli.py
github_standup_agent/config.py
github_standup_agent/context.py
github_standup_agent/hooks.py
github_standup_agent/instrumentation.py
github_standup_agent/py.typed
github_standup_agent/runner.py
github_standup_agent/agents/__init__.py
github_standup_agent/agents/coordinator.py
github_standup_agent/agents/data_gatherer.py
github_standup_agent/agents/summarizer.py
github_standup_agent/guardrails/__init__.py
github_standup_agent/guardrails/input_guardrails.py
github_standup_agent/guardrails/output_guardrails.py
github_standup_agent/output/__init__.py
github_standup_agent/tools/__init__.py
github_standup_agent/tools/clipboard.py
github_standup_agent/tools/feedback.py
github_standup_agent/tools/history.py
github_standup_agent/tools/github/__init__.py
github_standup_agent/tools/github/github_activity.py
github_standup_agent/tools/github/github_assigned.py
github_standup_agent/tools/github/github_comments.py
github_standup_agent/tools/github/github_commits.py
github_standup_agent/tools/github/github_events.py
github_standup_agent/tools/github/github_issues.py
github_standup_agent/tools/github/github_prs.py
github_standup_agent/tools/github/github_reviews.py
github_standup_agent/tools/slack/__init__.py
github_standup_agent/tools/slack/slack_client.py
github_standup_agent/tools/slack/slack_publish.py
github_standup_agent/tools/slack/slack_standups.py
github_standup_agent-0.3.3.dist-info/METADATA
github_standup_agent-0.3.3.dist-info/WHEEL
github_standup_agent-0.3.3.dist-info/entry_points.txt
github_standup_agent-0.3.3.dist-info/licenses/LICENSE
github_standup_agent-0.3.3.dist-info/RECORD
