Metadata-Version: 2.4
Name: github-standup-agent
Version: 0.3.3
Summary: AI-powered daily standup summaries from GitHub activity using OpenAI Agents SDK
Project-URL: Homepage, https://github.com/andymaguire/github-standup-agent
Project-URL: Repository, https://github.com/andymaguire/github-standup-agent
Project-URL: Documentation, https://github.com/andymaguire/github-standup-agent#readme
Author-email: Andrew Maguire <andrewm4894@gmail.com>
License-Expression: MIT
License-File: LICENSE
Keywords: agents,ai,cli,github,openai,standup
Classifier: Development Status :: 3 - Alpha
Classifier: Environment :: Console
Classifier: Intended Audience :: Developers
Classifier: License :: OSI Approved :: MIT License
Classifier: Programming Language :: Python :: 3
Classifier: Programming Language :: Python :: 3.11
Classifier: Programming Language :: Python :: 3.12
Classifier: Topic :: Software Development :: Version Control :: Git
Requires-Python: >=3.11
Requires-Dist: openai-agents>=0.0.7
Requires-Dist: platformdirs>=4.0.0
Requires-Dist: pydantic-settings>=2.0
Requires-Dist: pydantic>=2.0
Requires-Dist: pyperclip>=1.8.0
Requires-Dist: python-dotenv>=1.0.0
Requires-Dist: rich>=13.0
Requires-Dist: slack-sdk>=3.27.0
Requires-Dist: typer>=0.12.0
Provides-Extra: dev
Requires-Dist: mypy>=1.0; extra == 'dev'
Requires-Dist: pytest-asyncio>=0.23.0; extra == 'dev'
Requires-Dist: pytest>=8.0; extra == 'dev'
Requires-Dist: ruff>=0.4.0; extra == 'dev'
Provides-Extra: posthog
Requires-Dist: posthog>=7.7.0; extra == 'posthog'
